pyscholarly/__init__.py
pyscholarly/scholarly.py
pyscholarly-0.1.77.dist-info/LICENSE
pyscholarly-0.1.77.dist-info/METADATA
pyscholarly-0.1.77.dist-info/WHEEL
pyscholarly-0.1.77.dist-info/top_level.txt
pyscholarly-0.1.77.dist-info/RECORD
