Metadata-Version: 2.1
Name: pyscholarly
Version: 0.1.77
Summary: An async Python library for scraping Google Scholar profiles
Author-email: Rach Pradhan <me@rachit.ai>
Project-URL: Homepage, https://github.com/justrach/pyscholarly
Project-URL: Bug Tracker, https://github.com/justrach/pyscholarly/issues
Classifier: Development Status :: 3 - Alpha
Classifier: Intended Audience :: Science/Research
Classifier: License :: OSI Approved :: MIT License
Classifier: Programming Language :: Python :: 3
Classifier: Programming Language :: Python :: 3.8
Classifier: Programming Language :: Python :: 3.9
Classifier: Programming Language :: Python :: 3.10
Classifier: Programming Language :: Python :: 3.11
Classifier: Topic :: Scientific/Engineering :: Information Analysis
Requires-Python: >=3.8
License-File: LICENSE
Requires-Dist: playwright>=1.40.0
Requires-Dist: aiohttp>=3.8.0
Requires-Dist: kew>=0.1.4
